loggertools/__init__.py
loggertools/_version.py
loggertools/loggertools.py
loggertools-1.0.dist-info/LICENSE
loggertools-1.0.dist-info/METADATA
loggertools-1.0.dist-info/WHEEL
loggertools-1.0.dist-info/top_level.txt
loggertools-1.0.dist-info/RECORD
