Metadata-Version: 2.1
Name: loggertools
Version: 1.0
Summary: loggertools: a Python port of the Control File Functions of Loggertools, the Logger Tools Software of Olaf Kolle, MPI-BGC Jena, (c) 2012.
Home-page: https://github.com/mcuntz/loggertools
Author: Matthias Cuntz, Olaf Kolle
Author-email: mc@macu.de
Maintainer: Matthias Cuntz
Maintainer-email: mc@macu.de
License: MIT
Project-URL: Documentation, https://mcuntz.github.io/loggertools/
Project-URL: Source, https://github.com/mcuntz/loggertools
Project-URL: Tracker, https://github.com/mcuntz/loggertools/issues
Project-URL: Changelog, https://github.com/mcuntz/loggertools/blob/main/CHANGELOG.rst
Platform: any
Classifier: Development Status :: 5 - Production/Stable
Classifier: Intended Audience :: Developers
Classifier: Intended Audience :: End Users/Desktop
Classifier: Intended Audience :: Science/Research
Classifier: License :: OSI Approved :: MIT License
Classifier: Natural Language :: English
Classifier: Operating System :: MacOS
Classifier: Operating System :: MacOS :: MacOS X
Classifier: Operating System :: Microsoft
Classifier: Operating System :: Microsoft :: Windows
Classifier: Operating System :: POSIX
Classifier: Operating System :: Unix
Classifier: Programming Language :: Python
Classifier: Programming Language :: Python :: 3
Classifier: Programming Language :: Python :: 3 :: Only
Classifier: Programming Language :: Python :: 3.8
Classifier: Programming Language :: Python :: 3.9
Classifier: Programming Language :: Python :: 3.10
Classifier: Programming Language :: Python :: 3.11
Classifier: Topic :: Scientific/Engineering
Classifier: Topic :: Scientific/Engineering :: Atmospheric Science
Classifier: Topic :: Scientific/Engineering :: Hydrology
Classifier: Topic :: Scientific/Engineering :: Physics
Classifier: Topic :: Software Development
Classifier: Topic :: Utilities
Requires-Python: >=3.8
License-File: LICENSE
Requires-Dist: numpy
Provides-Extra: doc
Requires-Dist: numpydoc (<2,>=1.1) ; extra == 'doc'
Requires-Dist: jinja2 (>=2) ; extra == 'doc'
Requires-Dist: sphinx (<4,>=3) ; extra == 'doc'
Provides-Extra: test
Requires-Dist: coverage[toml] (<6,>=5.2.1) ; extra == 'test'
Requires-Dist: pytest (<7,>=6.0) ; extra == 'test'
Requires-Dist: pytest-cov (<3,>=2.11.0) ; extra == 'test'
